otscli/__init__.py
otscli/otscli.py
otscli-0.0.2.dist-info/DESCRIPTION.rst
otscli-0.0.2.dist-info/METADATA
otscli-0.0.2.dist-info/RECORD
otscli-0.0.2.dist-info/WHEEL
otscli-0.0.2.dist-info/entry_points.txt
otscli-0.0.2.dist-info/metadata.json
otscli-0.0.2.dist-info/top_level.txt
