Metadata-Version: 2.0
Name: otscli
Version: 0.0.2
Summary: Console client for one time secret.
Home-page: https://github.com/verdel/otscli
Author: Vadim Aleksandrov
Author-email: valeksandrov@me.com
License: MIT
Keywords: otscli
Platform: UNKNOWN
Classifier: Development Status :: 2 - Pre-Alpha
Classifier: Intended Audience :: Developers
Classifier: License :: OSI Approved :: MIT License
Classifier: Natural Language :: English
Classifier: Programming Language :: Python :: 2
Classifier: Programming Language :: Python :: 2.7
Classifier: Programming Language :: Python :: 3
Classifier: Programming Language :: Python :: 3.3
Classifier: Programming Language :: Python :: 3.4
Classifier: Programming Language :: Python :: 3.5
Requires-Dist: requests (>=2.0)
